kotti_rstdocument
