Metadata-Version: 1.0
Name: kotti-rstdocument
Version: 0.2
Summary: Use reStructuredText documents in your Kotti site
Home-page: http://pypi.python.org/pypi/kotti_rstdocument
Author: Daniel Newton
Author-email: djpnewton@gmail.com
License: MIT
Keywords: rst restructuredtext kotti cms pylons pyramid
Platform: UNKNOWN
Classifier: Programming Language :: Python
Classifier: Framework :: Pylons
Classifier: Topic :: Internet :: WWW/HTTP
Classifier: Topic :: Internet :: WWW/HTTP :: Dynamic Content
Classifier: Topic :: Internet :: WWW/HTTP :: WSGI :: Application
Classifier: License :: OSI Approved :: MIT License
